LICENSE
MANIFEST.in
README.md
setup.py
docums_with_pdf.egg-info/PKG-INFO
docums_with_pdf.egg-info/SOURCES.txt
docums_with_pdf.egg-info/dependency_links.txt
docums_with_pdf.egg-info/entry_points.txt
docums_with_pdf.egg-info/requires.txt
docums_with_pdf.egg-info/top_level.txt
mkdocs_with_pdf/__init__.py
mkdocs_with_pdf/cover.py
mkdocs_with_pdf/generator.py
mkdocs_with_pdf/options.py
mkdocs_with_pdf/plugin.py
mkdocs_with_pdf/toc.py
mkdocs_with_pdf/drivers/__init__.py
mkdocs_with_pdf/drivers/event_hook.py
mkdocs_with_pdf/drivers/headless_chrome.py
mkdocs_with_pdf/preprocessor/__init__.py
mkdocs_with_pdf/preprocessor/links/__init__.py
mkdocs_with_pdf/preprocessor/links/transform.py
mkdocs_with_pdf/preprocessor/links/util.py
mkdocs_with_pdf/styles/__init__.py
mkdocs_with_pdf/templates/__init__.py
mkdocs_with_pdf/templates/template.py
mkdocs_with_pdf/templates/filters/__init__.py
mkdocs_with_pdf/templates/filters/barcode.py
mkdocs_with_pdf/templates/filters/datetime.py
mkdocs_with_pdf/templates/filters/qrcode.py
mkdocs_with_pdf/templates/filters/url.py
mkdocs_with_pdf/themes/__init__.py
mkdocs_with_pdf/themes/docums.py
mkdocs_with_pdf/themes/generic.py
mkdocs_with_pdf/themes/material.py
mkdocs_with_pdf/utils/__init__.py
mkdocs_with_pdf/utils/emoji_util.py
mkdocs_with_pdf/utils/iframe_util.py
mkdocs_with_pdf/utils/image_util.py
mkdocs_with_pdf/utils/layout_util.py
mkdocs_with_pdf/utils/section.py
mkdocs_with_pdf/utils/soup_util.py
mkdocs_with_pdf/utils/tabbed_set_util.py