Metadata-Version: 2.1
Name: docums-with-pdf
Version: 0.9.3
Summary: Generate a single PDF file from Docums repository
Home-page: https://github.com/khanhduy1407/docums-with-pdf
Author: NKDuy
Author-email: kn145660@gmail.com
License: MIT
Keywords: docums pdf weasyprint
Platform: UNKNOWN
Classifier: Development Status :: 4 - Beta
Classifier: Intended Audience :: Developers
Classifier: Intended Audience :: Information Technology
Classifier: License :: OSI Approved :: MIT License
Classifier: Programming Language :: Python
Classifier: Programming Language :: Python :: 3 :: Only
Classifier: Programming Language :: Python :: 3.6
Classifier: Programming Language :: Python :: 3.7
Classifier: Programming Language :: Python :: 3.8
Classifier: Programming Language :: Python :: 3.9
Requires-Python: >=3.6
